bempy/__init__.py
bempy/base.py
bempy/builder.py
bempy/utils/__init__.py
bempy/utils/args.py
bempy/utils/parser.py
bempy/utils/structer.py
bempy-0.3.1.dist-info/LICENSE
bempy-0.3.1.dist-info/METADATA
bempy-0.3.1.dist-info/WHEEL
bempy-0.3.1.dist-info/top_level.txt
bempy-0.3.1.dist-info/RECORD
