Metadata-Version: 2.1
Name: bempy
Version: 0.3.1
Summary: BEM-based class construction
Home-page: http://github.com/fefa4ka/bempy
Author: Alexander Kondratev
Author-email: alex@nder.work
License: GPLv3+
Classifier: Intended Audience :: Developers
Classifier: Programming Language :: Python :: 3
Classifier: License :: OSI Approved :: GNU General Public License v3 or later (GPLv3+)
Classifier: Operating System :: OS Independent
Classifier: Topic :: Software Development :: Libraries :: Python Modules
License-File: LICENSE
